MANIFEST.in
README.md
setup.py
stackexchange/__init__.py
stackexchange.egg-info/PKG-INFO
stackexchange.egg-info/SOURCES.txt
stackexchange.egg-info/dependency_links.txt
stackexchange.egg-info/requires.txt
stackexchange.egg-info/top_level.txt
stackexchange/api/__init__.py
stackexchange/api/_api_base.py
stackexchange/api/_api_reader.py
stackexchange/api/_api_request.py
stackexchange/rest/__init__.py
stackexchange/rest/answer.py
stackexchange/rest/questions.py
stackexchange/rest/search.py