Metadata-Version: 1.1
Name: stackexchange
Version: 0.5.0
Summary: Stackexchange API for Python
Home-page: https://github.com/plasmashadow/stackexchange.git
Author: plasmashadow
Author-email: plasmashadowx@gmail.com
License: MIT License
Platform: UNKNOWN
Classifier: Programming Language :: Python
Classifier: Programming Language :: Python :: 2
Classifier: Intended Audience :: Developers
